telegraf_client-0.1.38.dist-info/METADATA
telegraf_client-0.1.38.dist-info/WHEEL
telegraf_client-0.1.38.dist-info/licenses/LICENSE
telegraf_client/__init__.py
telegraf_client/telegraf_client.cpython-312-aarch64-linux-gnu.so
telegraf_client-0.1.38.dist-info/RECORD
