Metadata-Version: 2.4
Name: telegraf-client
Version: 0.1.38
Classifier: Development Status :: 4 - Beta
Classifier: Intended Audience :: Developers
Classifier: License :: OSI Approved :: MIT License
Classifier: Programming Language :: Python :: 3
Classifier: Programming Language :: Python :: 3.12
Classifier: Programming Language :: Python :: 3 :: Only
Classifier: Programming Language :: Rust
Classifier: Topic :: Software Development :: Libraries :: Python Modules
Classifier: Topic :: System :: Monitoring
Requires-Dist: pytest ; extra == 'dev'
Requires-Dist: maturin>=1.9.6 ; extra == 'build'
Requires-Dist: twine==6.0.1 ; extra == 'build'
Provides-Extra: dev
Provides-Extra: build
License-File: LICENSE
Summary: Python bindings for the telegraf Rust client
Keywords: telegraf,metrics,monitoring,rust,python
Author: telegraf-client contributors
License: MIT
Requires-Python: >=3.12, <3.13
Project-URL: Homepage, https://github.com/KidziaK/telegraf_client
Project-URL: Repository, https://github.com/KidziaK/telegraf_client
